browser_hub/__init__.py
browser_hub/config.py
browser_hub/main.py
browser_hub/processes.py
browser_hub-0.0.5.dist-info/METADATA
browser_hub-0.0.5.dist-info/WHEEL
browser_hub-0.0.5.dist-info/entry_points.txt
browser_hub-0.0.5.dist-info/licenses/LICENSE
browser_hub-0.0.5.dist-info/RECORD
