Metadata-Version: 2.4
Name: browser-hub
Version: 0.0.5
Summary: Manage multiple browser instances without hassles.
Project-URL: Homepage, https://github.com/amirkarimi/browser-hub
Project-URL: Issues, https://github.com/amirkarimi/browser-hub/issues
Author-email: Amir Karimi <me@amirkarimi.dev>
License-File: LICENSE
Classifier: License :: OSI Approved :: MIT License
Classifier: Operating System :: POSIX
Classifier: Programming Language :: Python :: 3
Classifier: Topic :: Internet :: WWW/HTTP :: Browsers
Classifier: Topic :: Utilities
Requires-Python: >=3.9
Requires-Dist: psutil==5.9.*
Requires-Dist: pydantic==2.11.*
